Workbook

Sheet Content
B3: Case Study
B16: Hot Dog Sales Case
B17: Basic cell operation
B18: Format as table
B19: VLOOKUP
B20: Concatenate
B21: Charts
B22: Slicers
B23: Conditional Formatting
B24: Pivot Tables

Sheet Case
B2: Case DESCRIPTION | C2: A Company sells fast food products in different locations of Washington (USA). We have had access to business data, summarized in three tables: . AREAS. Describes where the different point of sales (street vending carts) are located. . PRODUCTS. List of product names and ID's . SALES. Sales data. Special mention to: UnitCost. Cost per unit of the product. Price. Product selling price.
B4: Objective | C4: Which is the Product with best margin? Which is the Product that generates more profit? Which is the Area that generates more profit? Which is the Product in this Area that generates more profit? What is the percentage of the best profit product to total sales? Have sales of each product evolved in the same way through years?
B6: Actions BLOCK1 | C6: . Add format to the tables of tabs 'Areas'(yellow format), 'Products'(blue format) and 'Sales' (Green format) . Assign names to these tables (use tab names). . Assign colors to the tabs containing the above tables (same colors used in format)
B8: Actions BLOCK2 | C8: . Create column 'NetSales'='GrossSales'-'Discounts' . Create column 'UnitMargin'='Price'-'UnitCost' . Create column 'COGS' = 'UnitCost'*'Quantity' . Create column 'NetProfit' = 'NetSales'-'COGS' . Create column 'ProductName'that shows the name of the product described in 'Products' table. . Create column 'AreaName' that show the area where each sale took place, according to 'Areas' table. . Create column 'Date' joining the year with the quarter information (e.g. '2010Q1') . Add currency units ('€') to required columns. . Use only 1 decimal place in currency columns. . Add subtotals in 'NetSales' (sum of values) and 'StandID' (count of values) columns
B10: Actions BLOCK3 | C10: . Calculate the number of sales in each Area . Count the number of sales in 2010Q4 and 2011Q2 using COUNTIF . Calculate Sum of NetSales in 2010Q2 greater than 10.000€ using SUMIF . Calculate Sum of NetSales in 2010Q2 greater than 10.000€ using SUMIFS
B12: Actions BLOCK4 | C12: . Create a Pivot Table that relates 'UnitMargin' versus 'ProductName'. Average the values of 'UnitMargin' . Create a Pivot Table that relates 'NetProfit' versus 'ProductName'. . Create a Pivot Table that relates 'NetSales'and 'NetProfit' versus 'AreaNames'. . Assign appropiate names to the tables fields. . Sort last two tables by 'NetProfit', from largest to smallest . Use a Blue style in the first table (Products) and a 'Yellow' in the second (Areas) . Add to all Pivot Tables a Bar conditional format
B14: Actions BLOCK5 | C14: . Create a Pivot Table that relates 'NetProfit' versus 'Years' (columns) versus 'ProductName' (Rows). . Add a Sparkline to see year by year evolution of sales.
B16: Actions BLOCK6 | C16: . Create a Pie chart with 'TotalProfit' by 'ProductName' . Show percentages as data labels. Increase the font size up to 12 . Add the title 'Net Profit sales by Product' . Locate the legend at the bottom
B18: Actions BLOCK7 | C18: . Answer the questions in the 'Answers' tab

Sheet Areas
A1: StandID | B1: AreaName | C1: Address
A2: 1001 | B2: Downtown Seattle | C2: 400 Pine St, Seattle, WA 98101
A3: 1002 | B3: Capitol Hill | C3: 925 E. Pike St. Seattle, WA 98122
A4: 1003 | B4: Belltown | C4: 2600 Western Ave, Seattle, WA 98121
A5: 1004 | B5: Pioneer Square | C5: 1010 1st Ave, Seattle, WA 98104
A6: 1005 | B6: South Lake Union | C6: 320 Westlake Ave N, Seattle, WA 98109

Sheet Products
A1: ProductID | B1: ProductName
A2: A10011 | B2: Beef Hotdog
A3: B10021 | B3: Bratwurst
A4: C10031 | B4: Tofu dog
A5: D10041 | B5: Potato Chips
A6: E10051 | B6: Cookie
A7: F10061 | B7: Soda
A8: G10071 | B8: Water

Sheet Sales
A1: StandId | B1: Year | C1: Quarter | D1: Product | E1: UnitCost | F1: Price | G1: Qty | H1: GrossSales | I1: Discounts
A2: 1003 | B2: 2010 | C2: Q1 | D2: A10011 | E2: 0.91 | F2: 3.99 | G2: 1416 | H2: =Sales!$F2*Sales!$G2 -> 5649.84 | I2: 395.4888
A3: 1003 | B3: 2010 | C3: Q2 | D3: A10011 | E3: 0.91 | F3: 3.99 | G3: 1698 | H3: =Sales!$F3*Sales!$G3 -> 6775.02 | I3: 745.2522
A4: 1003 | B4: 2010 | C4: Q3 | D4: A10011 | E4: 0.91 | F4: 3.99 | G4: 1521 | H4: =Sales!$F4*Sales!$G4 -> 6068.79 | I4: 0
A5: 1003 | B5: 2010 | C5: Q4 | D5: A10011 | E5: 0.91 | F5: 3.99 | G5: 1435 | H5: =Sales!$F5*Sales!$G5 -> 5725.65 | I5: 171.7695
A6: 1002 | B6: 2010 | C6: Q1 | D6: A10011 | E6: 0.91 | F6: 3.99 | G6: 1344 | H6: =Sales!$F6*Sales!$G6 -> 5362.56 | I6: 482.6304
A7: 1002 | B7: 2010 | C7: Q2 | D7: A10011 | E7: 0.91 | F7: 3.99 | G7: 2069 | H7: =Sales!$F7*Sales!$G7 -> 8255.31 | I7: 0
A8: 1002 | B8: 2010 | C8: Q3 | D8: A10011 | E8: 0.91 | F8: 3.99 | G8: 2662 | H8: =Sales!$F8*Sales!$G8 -> 10621.38 | I8: 1380.7794
A9: 1002 | B9: 2010 | C9: Q4 | D9: A10011 | E9: 0.91 | F9: 3.99 | G9: 2478 | H9: =Sales!$F9*Sales!$G9 -> 9887.22 | I9: 1285.3386
A10: 1001 | B10: 2010 | C10: Q1 | D10: A10011 | E10: 0.91 | F10: 3.99 | G10: 2604 | H10: =Sales!$F10*Sales!$G10 -> 10389.96 | I10: 103.8996
A11: 1001 | B11: 2010 | C11: Q2 | D11: A10011 | E11: 0.91 | F11: 3.99 | G11: 1905 | H11: =Sales!$F11*Sales!$G11 -> 7600.95 | I11: 608.076
A12: 1001 | B12: 2010 | C12: Q3 | D12: A10011 | E12: 0.91 | F12: 3.99 | G12: 1942 | H12: =Sales!$F12*Sales!$G12 -> 7748.58 | I12: 1162.287
A13: 1001 | B13: 2010 | C13: Q4 | D13: A10011 | E13: 0.91 | F13: 3.99 | G13: 1309 | H13: =Sales!$F13*Sales!$G13 -> 5222.91 | I13: 574.5201
... A561: 1005 | B561: 2013 | C561: Q4 | D561: G10071 | E561: 0.4 | F561: 1.5 | G561: 1769 | H561: =Sales!$F561*Sales!$G561 -> 2653.5 | I561: 371.49
A562: =SUBTOTAL(103,Sales!$A$2:$A$561) -> 560

Sheet Analysis
B2: Analysis

Sheet Answers
B2: Answers
B5: Which is the Product with best margin?
B7: Which is the Product that generates more profit?
B9: Which is the Area that generates more profit?
B11: Which is the Product in this Area that generates more profit?
B13: What is the percentage of the best product profit to total profit?
B15: Have sales of each product evolved in the same way through years?
